{
  "parts": [
    {
      "name": "Bumper",
      "localPosition": {
        "x": -0.00400018692,
        "y": -0.721000016,
        "z": 3.24300003
      },
      "localEuler": {
        "x": 0.0,
        "y": 0.0,
        "z": 0.0,
      },
      "localScale": {
        "x": 1.0,
        "y": 1.0,
        "z": 1.0
      }
    },
    {
      "name": "Body",
      "localPosition": {
        "x": 0.0,
        "y": 0.0,
        "z": 0.0
      },
      "localEuler": {
        "x": 0.0,
        "y": 0.0,
        "z": 0.0,
      },
      "localScale": {
        "x": 1.0,
        "y": 1.0,
        "z": 1.0
      }
    },
    {
      "name": "Lights",
      "localPosition": {
        "x": 0.0799999982,
        "y": -0.170000076,
        "z": 3.40999985
      },
      "localEuler": {
        "x": 0.0,
        "y": 0.0,
        "z": 0.0,
      },
      "localScale": {
        "x": 1.0,
        "y": 1.0,
        "z": 1.0
      }
    },
    {
      "name": "Tire_Left1",
      "localPosition": {
        "x": -1.18229997,
        "y": -1.1056,
        "z": 1.71469998
      },
      "localEuler": {
        "x": 0.0,
        "y": 0.0,
        "z": 0.0,
        "w": 1.0
      },
      "localScale": {
        "x": 1.0,
        "y": 1.0,
        "z": 1.0
      }
    },
    {
      "name": "Tire_Right1",

      "localPosition": {
        "x": -1.18229997,
        "y": -1.1056,
        "z": -1.70819998
      },
      "localEuler": {
        "x": 0.0,
        "y": 0.0,
        "z": 0.0
      },
      "localScale": {
        "x": 1.0,
        "y": 1.0,
        "z": 1.0
      }
    }
  ]
}
